qs_mps/Ising_gs_and_time_ev.py
qs_mps/TensorMultiplier.py
qs_mps/__init__.py
qs_mps/analytical_formulas_TFIC.py
qs_mps/checks.py
qs_mps/get_rdms.py
qs_mps/gs_multiprocessing.py
qs_mps/lattice.py
qs_mps/mpo_class.py
qs_mps/mps_class.py
qs_mps/sparse_hamiltonians_and_operators.py
qs_mps/utils.py
qs_mps/applications/__init__.py
qs_mps/applications/ANNNI/get_gs_DMRG.py
qs_mps/applications/ANNNI/get_observables_MPS.py
qs_mps/applications/ANNNI/ground_state_multiprocessing.py
qs_mps/applications/CLUSTER/get_gs_DMRG-xy.py
qs_mps/applications/CLUSTER/get_gs_DMRG.py
qs_mps/applications/CLUSTER/get_observables_MPS.py
qs_mps/applications/ISING/TEBD_different_chi.py
qs_mps/applications/ISING/TEBD_different_delta.py
qs_mps/applications/ISING/__init__.py
qs_mps/applications/ISING/assess_time.py
qs_mps/applications/ISING/get_gs_DMRG.py
qs_mps/applications/ISING/get_gs_and_time_ev_EXACT.py
qs_mps/applications/ISING/get_observables_MPS.py
qs_mps/applications/ISING/plot_DMRG.py
qs_mps/applications/ISING/plot_TEBD.py
qs_mps/applications/XXZ/get_gs_DMRG.py
qs_mps/applications/Z2/__init__.py
qs_mps/applications/Z2/exact_hamiltonian.py
qs_mps/applications/Z2/get_gs_DMRG.py
qs_mps/applications/Z2/get_gs_EXACT.py
qs_mps/applications/Z2/get_observables_EXACT.py
qs_mps/applications/Z2/get_observables_MPS.py
qs_mps/applications/Z2/ground_state_multiprocessing.py
qs_mps/applications/Z2/multi_run_gs.py
qs_mps/applications/Z2/multi_run_obs.py
qs_mps/applications/Z2/plot_DMRG.py
qs_mps/applications/Z2/plot_animations.py
qs_mps/applications/Z2/string_energy_density_debug.py
qs_mps/applications/Z2/test_sparse_mpo.py
qs_mps/applications/Z2/time_ev_debug.py
qs_mps/applications/Z2/vacuum_sector.py
qs_mps/applications/Z2/notebooks/__init__.py
qs_mps-2024.0.4.dist-info/LICENSE
qs_mps-2024.0.4.dist-info/METADATA
qs_mps-2024.0.4.dist-info/WHEEL
qs_mps-2024.0.4.dist-info/top_level.txt
qs_mps-2024.0.4.dist-info/RECORD
