Metadata-Version: 2.1
Name: qs-mps
Version: 2024.0.4
Summary: Quantum Simulation with Matrix Product State, a Tensor network method for the study of Quantum Systems
Author-email: Francesco Di Marcantonio <francesco.di.marcantonio@cern.ch>
Maintainer-email: Francesco Di Marcantonio <francesco.di.marcantonio@cern.ch>
License: Apache License
Project-URL: Repository, https://github.com/Fradm98/mps.git
Keywords: tensor network,matrix product state,quantum many-body system,quantum phase transition
Classifier: License :: OSI Approved :: Apache Software License
Classifier: Operating System :: Microsoft :: Windows
Classifier: Topic :: Scientific/Engineering :: Physics
Classifier: Programming Language :: Python :: 3.12
Requires-Python: >=3.6
License-File: LICENSE
Requires-Dist: numpy
Requires-Dist: scipy
Requires-Dist: ncon
Requires-Dist: matplotlib
Requires-Dist: jupyter
Requires-Dist: sympy
Provides-Extra: tests
Requires-Dist: pytest ; extra == 'tests'
Requires-Dist: coverage ; extra == 'tests'
Requires-Dist: pytest-cov ; extra == 'tests'
